mandr/__init__.py
mandr-0.0.0.dist-info/METADATA
mandr-0.0.0.dist-info/WHEEL
mandr-0.0.0.dist-info/top_level.txt
mandr-0.0.0.dist-info/RECORD
